MANIFEST.in
README.rst
setup.py
funniest/__init__.py
funniest/command_line.py
funniest/joke_file.py
funniest_tlelson.egg-info/PKG-INFO
funniest_tlelson.egg-info/SOURCES.txt
funniest_tlelson.egg-info/dependency_links.txt
funniest_tlelson.egg-info/entry_points.txt
funniest_tlelson.egg-info/not-zip-safe
funniest_tlelson.egg-info/requires.txt
funniest_tlelson.egg-info/top_level.txt