Metadata-Version: 1.1
Name: funniest-tlelson
Version: 0.1
Summary: The funniest joke in the world
Home-page: UNKNOWN
Author: timbo
Author-email: tim.l.elson@gmail.com
License: MIT
Keywords: funniest joke comedy flying circus
Platform: UNKNOWN
Classifier: Development Status :: 3 - Alpha
Classifier: License :: OSI Approved :: MIT License
Classifier: Programming Language :: Python :: 3.5
Classifier: Topic :: Text Processing :: Linguistic
